reptyl/__init__.py
reptyl/reptyl.py
reptyl-2.0.0.1.dist-info/LICENSE.md
reptyl-2.0.0.1.dist-info/METADATA
reptyl-2.0.0.1.dist-info/WHEEL
reptyl-2.0.0.1.dist-info/top_level.txt
reptyl-2.0.0.1.dist-info/RECORD
