Metadata-Version: 2.1
Name: reptyl
Version: 2.0.0.1
Summary: Reptyl is free-to-use a cross-platform command line shell that supports execution of commands in natural language
Author: 0ut0flin3
Author-email: 0ut0flin3 <0ut0flin3@protonmail.com>
License: Apache License
Project-URL: Homepage, https://github.com/0ut0flin3/Reptyl
Keywords: reptyl,shell,command-line,gpt-3,natural language
Classifier: License :: OSI Approved :: Apache Software License
Classifier: Programming Language :: Python
Classifier: Programming Language :: Python :: 3
Requires-Python: >=3
License-File: LICENSE.md
